<?xml version="1.0" encoding="UTF-8"?>
<objects serializationModel="Studio.02.02.00">
	<object class="AudioFile" id="{ea144899-2d6d-4ccb-913b-26fc2fe80a25}">
		<property name="assetPath">
			<value>21 Last Words.wav</value>
		</property>
		<property name="isStreaming">
			<value>true</value>
		</property>
		<property name="frequencyInKHz">
			<value>48</value>
		</property>
		<property name="channelCount">
			<value>2</value>
		</property>
		<property name="length">
			<value>184.83333333333334</value>
		</property>
		<relationship name="masterAssetFolder">
			<destination>{a3b346cc-7f6c-4b51-acb8-491971281eb5}</destination>
		</relationship>
	</object>
</objects>
